boostsa/__init__.py
boostsa/boostsa.py
boostsa/util201217.py
boostsa-0.2.13.dist-info/AUTHORS.rst
boostsa-0.2.13.dist-info/LICENSE
boostsa-0.2.13.dist-info/METADATA
boostsa-0.2.13.dist-info/WHEEL
boostsa-0.2.13.dist-info/top_level.txt
boostsa-0.2.13.dist-info/RECORD
