Metadata-Version: 2.1
Name: boostsa
Version: 0.2.13
Summary: A package to compute bootstrap sampling significance test
Home-page: https://github.com/fornaciari/bootstrap
Author: Tommaso Fornaciari
Author-email: fornaciari@unibocconi.it
License: MIT license
Platform: UNKNOWN
Classifier: Programming Language :: Python :: 3.7
Classifier: License :: OSI Approved :: GNU General Public License v3 (GPLv3)
Requires-Python: >=3.6
License-File: LICENSE
License-File: AUTHORS.rst
Requires-Dist: pip (==21.0.1)
Requires-Dist: wheel (==0.37.1)
Requires-Dist: twine (==3.3.0)
Requires-Dist: scipy (==1.7.3)
Requires-Dist: tqdm
Requires-Dist: pandas
Requires-Dist: numpy
Requires-Dist: sklearn
